[
  {
    "Id": "jenlooper-cactus",
    "img": "https://bucket.nhanh.vn/store/7534/ps/20191015/19090163_HOc_1000x1000.JPG",
    "Name": "cute1",
    "Price": 1.99
  },
  {
    "Id": "jenlooper-light",
    "img": "https://encrypted-tbn0.gstatic.com/images?q=tbn%3AANd9GcShto68vAf9f2B9van3rlO3ER5TxDyuqLacuA&usqp=CAU",
    "Name": "cute2",
    "Price": 2.99
  },
  {
    "Id": "jenlooper-lightshow",
    "img": "https://encrypted-tbn0.gstatic.com/images?q=tbn%3AANd9GcQcxCSUI6oIgyhutDgPH3q1L4O7bF_rAiJegg&usqp=CAU",
    "Name": "cute3",
    "Price": 1.99
  },
  {
    "Id": "jenlooper-survival",
    "Maker": "jenlooper",
    "img": "https://cdn.muabannhanh.com/asset/frontend/img/gallery/2020/06/05/5eda2c8450902_1591356548.jpeg",
    "Name": "cute4",
    "Price": 3.99
  },
  {
    "Id": "sailorhg-bubblesortpic",
    "img": "https://images.foody.vn/images/16996181_1929275203973103_6814426632011330123_n.jpg",
    "Name": "cute5",
    "Price": 2.99
  },
  {
    "Id": "sailorhg-corsage",
    "img": "https://cf.shopee.vn/file/7e3f37485534fb3c31eaaa827c68342c",
    "Name": "cut6",
    "Price": 2.66
  },
  {
    "Id": "sailorhg-kit",
    "img": "https://storage.googleapis.com/cdn.nhanh.vn/store/7534/ps/20200808/moc_treo_do_dinosaur_park__20072032_xx_.jpg",
    "Name": "cute7",
    "Price": 4.10
  },
  {
    "Id": "sailorhg-led",
    "img": "https://i2.wp.com/thietkenoithateco.com/wp-content/uploads/2017/10/do-gom-su-gia-re-truoc-nha-4.jpg?resize=643%2C857&ssl=1",
    "Name": "cute8",
    "Price": 3.22

  },
  {
    "Id": "selinazawacki-soi-shirt",
    "img": "https://cf.shopee.vn/file/bffd3a9d5e72ccf9e5d35d8c682a7f20_tn",
    "Name": "cute9",
    "Price": 2.13
  },
  {
    "Id": "selinazawacki-soi-pins",
    "img": "https://i.pinimg.com/originals/6b/d6/b2/6bd6b2966e500781ef12399cb22bb63b.jpg",
    "Name": "cute10",
    "Price": 3.45
  },
  {
    "Id": "vogueandcode-hipster-dev-bro",
    "Name": "cute11",
    "img": "https://golmart.vn/wp-content/uploads/2020/05/mot-so-san-pham-sieu-de-thuong-tai-cay-dau-to.jpeg",
    "Price": 13
  },
  {
    "Id": "vogueandcode-pretty-girls-code-tee",
    "Name": "cute12",
    "img": "https://encrypted-tbn0.gstatic.com/images?q=tbn%3AANd9GcTD4Hy-3rub1cR2XbU5YcVQczTn4mmNbIHocA&usqp=CAU",
    "Price": 23
  },
  {
    "Id": "vogueandcode-ruby-sis-2",
    "Name": "cute13",
    "img": "https://storage.googleapis.com/cdn.nhanh.vn/store2/66246/ps/20200328/28302020113014_IMG_4520.JPG",
    "Price": 2.33
  },
  {
    "Id": "selinazawacki-moon",
    "Name": "cute14",
    "img": "https://encrypted-tbn0.gstatic.com/images?q=tbn%3AANd9GcR8idVXyCPSi65uhCL1pgL_FLZq1Auq8ou-EQ&usqp=CAU",
    "Price": 11
  },
  {
    "Id": "selinazawacki-shirt",
    "Name": "cute15",
    "img": "https://cf.shopee.vn/file/5a945d40deefc2f536fb1fe872aa0a29",
    "Price": 18
  }
]